{
  "persons": [
    {
      "name": "Arto Hellas",
      "number": "040-123456",
      "id": "1"
    },
    {
      "name": "Ada Lovelace",
      "number": "39-44-5323523",
      "id": "2"
    },
    {
      "name": "Dan Abramov",
      "number": "12-43-234345",
      "id": "3"
    },
    {
      "name": "Mary Poppendieck",
      "number": "39-23-6423122",
      "id": "4"
    },
    {
      "id": "70f6",
      "name": "Sergio",
      "number": "654666666"
    },
    {
      "id": "cf05",
      "name": "Maria",
      "number": "54987456123"
    },
    {
      "id": "e9f9",
      "name": "Pedro",
      "number": "456789"
    },
    {
      "id": "ddcf",
      "name": "Hola",
      "number": "777"
    },
    {
      "id": "6212",
      "name": "Adios",
      "number": "8888"
    }
  ]
}